Workbook

Sheet Reporte Agosto 2026
A1: REPORTE DE PORTAL UPLOADS — AGOSTO 2026
A2: Resolution Time = Resolved − Submit. Distribución y portal filtrados a agosto; la tabla mensual muestra todos los meses.
A4: RESOLUTION TIME POR MES
A5: Mes | B5: # Uploads | C5: Resueltos | D5: Prom. horas | E5: Prom. días | F5: % mismo día
A6: 2026-06 | B6: =COUNTIF('Datos (calculo)'!$H$2:$H$169,"2026-06") | C6: =COUNTIFS('Datos (calculo)'!$H$2:$H$169,"2026-06",'Datos (calculo)'!$F$2:$F$169,">=0") | D6: =IFERROR(ROUND(AVERAGEIF('Datos (calculo)'!$H$2:$H$169,"2026-06",'Datos (calculo)'!$F$2:$F$169),1),0) | E6: =IFERROR(ROUND(AVERAGEIF('Datos (calculo)'!$H$2:$H$169,"2026-06",'Datos (calculo)'!$G$2:$G$169),1),0) | F6: =IFERROR(COUNTIFS('Datos (calculo)'!$H$2:$H$169,"2026-06",'Datos (calculo)'!$F$2:$F$169,"<24")/COUNTIFS('Datos (calculo)'!$H$2:$H$169,"2026-06",'Datos (calculo)'!$F$2:$F$169,">=0"),0)
A7: 2026-07 | B7: =COUNTIF('Datos (calculo)'!$H$2:$H$169,"2026-07") | C7: =COUNTIFS('Datos (calculo)'!$H$2:$H$169,"2026-07",'Datos (calculo)'!$F$2:$F$169,">=0") | D7: =IFERROR(ROUND(AVERAGEIF('Datos (calculo)'!$H$2:$H$169,"2026-07",'Datos (calculo)'!$F$2:$F$169),1),0) | E7: =IFERROR(ROUND(AVERAGEIF('Datos (calculo)'!$H$2:$H$169,"2026-07",'Datos (calculo)'!$G$2:$G$169),1),0) | F7: =IFERROR(COUNTIFS('Datos (calculo)'!$H$2:$H$169,"2026-07",'Datos (calculo)'!$F$2:$F$169,"<24")/COUNTIFS('Datos (calculo)'!$H$2:$H$169,"2026-07",'Datos (calculo)'!$F$2:$F$169,">=0"),0)
A8: 2026-08 | B8: =COUNTIF('Datos (calculo)'!$H$2:$H$169,"2026-08") | C8: =COUNTIFS('Datos (calculo)'!$H$2:$H$169,"2026-08",'Datos (calculo)'!$F$2:$F$169,">=0") | D8: =IFERROR(ROUND(AVERAGEIF('Datos (calculo)'!$H$2:$H$169,"2026-08",'Datos (calculo)'!$F$2:$F$169),1),0) | E8: =IFERROR(ROUND(AVERAGEIF('Datos (calculo)'!$H$2:$H$169,"2026-08",'Datos (calculo)'!$G$2:$G$169),1),0) | F8: =IFERROR(COUNTIFS('Datos (calculo)'!$H$2:$H$169,"2026-08",'Datos (calculo)'!$F$2:$F$169,"<24")/COUNTIFS('Datos (calculo)'!$H$2:$H$169,"2026-08",'Datos (calculo)'!$F$2:$F$169,">=0"),0)
A9: TOTAL | B9: =SUM(B6:B8) | C9: =SUM(C6:C8) | D9: =ROUND(AVERAGE('Datos (calculo)'!$F$2:$F$169),1) | E9: =ROUND(AVERAGE('Datos (calculo)'!$G$2:$G$169),1) | F9: =IFERROR(COUNTIFS('Datos (calculo)'!$F$2:$F$169,"<24")/COUNT('Datos (calculo)'!$F$2:$F$169),0)
A12: DISTRIBUCIÓN POR TIEMPO DE RESOLUCIÓN — AGOSTO
A13: Rango | B13: # Uploads | C13: % del total
A14: Mismo día (< 24 h) | B14: =COUNTIFS('Datos (calculo)'!$H$2:$H$169,"2026-08",'Datos (calculo)'!$F$2:$F$169,"<24") | C14: =IFERROR(B14/COUNTIFS('Datos (calculo)'!$H$2:$H$169,"2026-08",'Datos (calculo)'!$F$2:$F$169,">=0"),0)
A15: 1 – 2 días | B15: =COUNTIFS('Datos (calculo)'!$H$2:$H$169,"2026-08",'Datos (calculo)'!$F$2:$F$169,">=24",'Datos (calculo)'!$F$2:$F$169,"<48") | C15: =IFERROR(B15/COUNTIFS('Datos (calculo)'!$H$2:$H$169,"2026-08",'Datos (calculo)'!$F$2:$F$169,">=0"),0)
A16: 2 – 4 días | B16: =COUNTIFS('Datos (calculo)'!$H$2:$H$169,"2026-08",'Datos (calculo)'!$F$2:$F$169,">=48",'Datos (calculo)'!$F$2:$F$169,"<96") | C16: =IFERROR(B16/COUNTIFS('Datos (calculo)'!$H$2:$H$169,"2026-08",'Datos (calculo)'!$F$2:$F$169,">=0"),0)
A17: 4 – 7 días | B17: =COUNTIFS('Datos (calculo)'!$H$2:$H$169,"2026-08",'Datos (calculo)'!$F$2:$F$169,">=96",'Datos (calculo)'!$F$2:$F$169,"<168") | C17: =IFERROR(B17/COUNTIFS('Datos (calculo)'!$H$2:$H$169,"2026-08",'Datos (calculo)'!$F$2:$F$169,">=0"),0)
A18: Más de 7 días | B18: =COUNTIFS('Datos (calculo)'!$H$2:$H$169,"2026-08",'Datos (calculo)'!$F$2:$F$169,">=168") | C18: =IFERROR(B18/COUNTIFS('Datos (calculo)'!$H$2:$H$169,"2026-08",'Datos (calculo)'!$F$2:$F$169,">=0"),0)
A19: TOTAL | B19: =SUM(B14:B18) | C19: =IFERROR(B19/COUNTIFS('Datos (calculo)'!$H$2:$H$169,"2026-08",'Datos (calculo)'!$F$2:$F$169,">=0"),0)
A22: RESOLUTION TIME POR PORTAL — AGOSTO
A23: Portal | B23: # Uploads | C23: % del total | D23: Prom. días | E23: % mismo día
A24: Coupa | B24: =COUNTIFS('Datos (calculo)'!$I$2:$I$169,"Coupa",'Datos (calculo)'!$H$2:$H$169,"2026-08") | C24: =IFERROR(COUNTIFS('Datos (calculo)'!$I$2:$I$169,"Coupa",'Datos (calculo)'!$H$2:$H$169,"2026-08")/COUNTIFS('Datos (calculo)'!$H$2:$H$169,"2026-08",'Datos (calculo)'!$F$2:$F$169,">=0"),0) | D24: =IFERROR(ROUND(AVERAGEIFS('Datos (calculo)'!$G$2:$G$169,'Datos (calculo)'!$I$2:$I$169,"Coupa",'Datos (calculo)'!$H$2:$H$169,"2026-08"),1),0) | E24: =IFERROR(COUNTIFS('Datos (calculo)'!$I$2:$I$169,"Coupa",'Datos (calculo)'!$H$2:$H$169,"2026-08",'Datos (calculo)'!$F$2:$F$169,"<24")/COUNTIFS('Datos (calculo)'!$I$2:$I$169,"Coupa",'Datos (calculo)'!$H$2:$H$169,"2026-08"),0)
A25: Ariba | B25: =COUNTIFS('Datos (calculo)'!$I$2:$I$169,"Ariba",'Datos (calculo)'!$H$2:$H$169,"2026-08") | C25: =IFERROR(COUNTIFS('Datos (calculo)'!$I$2:$I$169,"Ariba",'Datos (calculo)'!$H$2:$H$169,"2026-08")/COUNTIFS('Datos (calculo)'!$H$2:$H$169,"2026-08",'Datos (calculo)'!$F$2:$F$169,">=0"),0) | D25: =IFERROR(ROUND(AVERAGEIFS('Datos (calculo)'!$G$2:$G$169,'Datos (calculo)'!$I$2:$I$169,"Ariba",'Datos (calculo)'!$H$2:$H$169,"2026-08"),1),0) | E25: =IFERROR(COUNTIFS('Datos (calculo)'!$I$2:$I$169,"Ariba",'Datos (calculo)'!$H$2:$H$169,"2026-08",'Datos (calculo)'!$F$2:$F$169,"<24")/COUNTIFS('Datos (calculo)'!$I$2:$I$169,"Ariba",'Datos (calculo)'!$H$2:$H$169,"2026-08"),0)
A26: Oracle | B26: =COUNTIFS('Datos (calculo)'!$I$2:$I$169,"Oracle",'Datos (calculo)'!$H$2:$H$169,"2026-08") | C26: =IFERROR(COUNTIFS('Datos (calculo)'!$I$2:$I$169,"Oracle",'Datos (calculo)'!$H$2:$H$169,"2026-08")/COUNTIFS('Datos (calculo)'!$H$2:$H$169,"2026-08",'Datos (calculo)'!$F$2:$F$169,">=0"),0) | D26: =IFERROR(ROUND(AVERAGEIFS('Datos (calculo)'!$G$2:$G$169,'Datos (calculo)'!$I$2:$I$169,"Oracle",'Datos (calculo)'!$H$2:$H$169,"2026-08"),1),0) | E26: =IFERROR(COUNTIFS('Datos (calculo)'!$I$2:$I$169,"Oracle",'Datos (calculo)'!$H$2:$H$169,"2026-08",'Datos (calculo)'!$F$2:$F$169,"<24")/COUNTIFS('Datos (calculo)'!$I$2:$I$169,"Oracle",'Datos (calculo)'!$H$2:$H$169,"2026-08"),0)
A27: Taulia | B27: =COUNTIFS('Datos (calculo)'!$I$2:$I$169,"Taulia",'Datos (calculo)'!$H$2:$H$169,"2026-08") | C27: =IFERROR(COUNTIFS('Datos (calculo)'!$I$2:$I$169,"Taulia",'Datos (calculo)'!$H$2:$H$169,"2026-08")/COUNTIFS('Datos (calculo)'!$H$2:$H$169,"2026-08",'Datos (calculo)'!$F$2:$F$169,">=0"),0) | D27: =IFERROR(ROUND(AVERAGEIFS('Datos (calculo)'!$G$2:$G$169,'Datos (calculo)'!$I$2:$I$169,"Taulia",'Datos (calculo)'!$H$2:$H$169,"2026-08"),1),0) | E27: =IFERROR(COUNTIFS('Datos (calculo)'!$I$2:$I$169,"Taulia",'Datos (calculo)'!$H$2:$H$169,"2026-08",'Datos (calculo)'!$F$2:$F$169,"<24")/COUNTIFS('Datos (calculo)'!$I$2:$I$169,"Taulia",'Datos (calculo)'!$H$2:$H$169,"2026-08"),0)
A28: Portal por URL | B28: =COUNTIFS('Datos (calculo)'!$I$2:$I$169,"Portal por URL",'Datos (calculo)'!$H$2:$H$169,"2026-08") | C28: =IFERROR(COUNTIFS('Datos (calculo)'!$I$2:$I$169,"Portal por URL",'Datos (calculo)'!$H$2:$H$169,"2026-08")/COUNTIFS('Datos (calculo)'!$H$2:$H$169,"2026-08",'Datos (calculo)'!$F$2:$F$169,">=0"),0) | D28: =IFERROR(ROUND(AVERAGEIFS('Datos (calculo)'!$G$2:$G$169,'Datos (calculo)'!$I$2:$I$169,"Portal por URL",'Datos (calculo)'!$H$2:$H$169,"2026-08"),1),0) | E28: =IFERROR(COUNTIFS('Datos (calculo)'!$I$2:$I$169,"Portal por URL",'Datos (calculo)'!$H$2:$H$169,"2026-08",'Datos (calculo)'!$F$2:$F$169,"<24")/COUNTIFS('Datos (calculo)'!$I$2:$I$169,"Portal por URL",'Datos (calculo)'!$H$2:$H$169,"2026-08"),0)
A29: Otros | B29: 3 | C29: =IFERROR(B29/COUNTIFS('Datos (calculo)'!$H$2:$H$169,"2026-08",'Datos (calculo)'!$F$2:$F$169,">=0"),0) | D29: 6.5 | E29: 0.667
A30: TOTAL | B30: =COUNTIFS('Datos (calculo)'!$H$2:$H$169,"2026-08",'Datos (calculo)'!$F$2:$F$169,">=0") | C30: =IFERROR(B30/COUNTIFS('Datos (calculo)'!$H$2:$H$169,"2026-08",'Datos (calculo)'!$F$2:$F$169,">=0"),0) | D30: =ROUND(AVERAGEIF('Datos (calculo)'!$H$2:$H$169,"2026-08",'Datos (calculo)'!$G$2:$G$169),1) | E30: =IFERROR(COUNTIFS('Datos (calculo)'!$H$2:$H$169,"2026-08",'Datos (calculo)'!$F$2:$F$169,"<24")/COUNTIFS('Datos (calculo)'!$H$2:$H$169,"2026-08",'Datos (calculo)'!$F$2:$F$169,">=0"),0)
A31: Portales normalizados (Ariba/ARIBA/ariba → Ariba, etc.). Fila 'Otros' agrupa portales de 1 upload.

Sheet Form Responses
A1: Message link | B1: Invoice Number | C1: Invoice Amount | D1: Portal Name or Link | E1: PO Number | F1: Special instructions / notes | G1: Submitted By | H1: Timestamp | I1: Status | J1: Emoji | K1: Assignment Trigger | L1: Collector assigned | M1: Message Timestamp | N1: Resolution Time
A2: https://qualtrics.slack.com/archives/C0A4LNX9SKW/p1766438869224269 | B2: test | C2: test | D2: test | E2: t | F2: t | G2: Alejandra Mendoza | H2: 46013.894 | I2: white_check_mark | J2: ✅ | K2: @alejandram | N2: #NUM!
A3: https://qualtrics.slack.com/archives/C02KP7NE6FP/p1780429636081279 | B3: QILNEW1915 | C3: 4970 | D3: BMW portal | E3: F495QVF | G3: Alejandra Mendoza | H3: 46175.574 | I3: white_check_mark | J3: ✅ | K3: @dreimers | L3: @dreimers | M3: 46176.467 | N3: 0 days 21 hrs
A4: https://qualtrics.slack.com/archives/C02KP7NE6FP/p1780504068556039 | B4: INV00020111 | C4: 1,892,527.00 AUD | D4: Ariba | E4: 3233945 | F4: Hi Diego, could you please help me with this upload? Thanks! | G4: Daniela Gomez Viscaino | H4: 46176.435 | I4: white_check_mark | J4: ✅ | K4: @dreimers | L4: @dreimers | M4: 46176.566 | N4: 0 days 3 hrs
A5: https://qualtrics.slack.com/archives/C02KP7NE6FP/p1780506681567439 | B5: Not Generated | C5: EUR 5,000.00 | D5: http://chorus-pro.gouv.fr | E5: 4500474677 | F5: SFDC Account: https://qualtrics.lightning.force.com/lightning/r/Account__c/0015000000kh2e6AAA/view SFDC Opp/Quote: https://qualtrics.lightning.force.com/lightning/r/Opportunity/006VH00000QU1FpYAL/view Request Details: Hi Team, Once the invoice is issued (SO case already created 🤓!), could you kindly manage the portal upload? Info: 1. Portal: Chorus Pro (http://chorus-pro.gouv.fr) 2. SIRET number: 93823061200013 3. Legal commitment number (PO number): 4500474677 AS:ZZ_C89C4CE975D948F8 | G5: Kaushal Hogade | H5: 46176.463 | I5: white_check_mark | J5: ✅ | K5: @dreimers | L5: @dreimers | M5: 46177.526 | N5: 1 days 1 hrs
A6: https://qualtrics.slack.com/archives/C02KP7NE6FP/p1780515629982839 | B6: INV00019964 | C6: 135239 | D6: Coupa | E6: MPO106786 | G6: Daniela Gomez Viscaino | H6: 46176.569 | I6: white_check_mark | J6: ✅ | K6: @dreimers | L6: @dreimers | M6: 46177.513 | N6: 0 days 22 hrs
A7: https://qualtrics.slack.com/archives/C02KP7NE6FP/p1780607713987399 | B7: 469020 | C7: 9038.14 | D7: Ariba | E7: PO604178 | F7: Hi team! Could please submit this invoice to the Ariba portal? If the invoice has been submitted, please just confirm, as the customer is not seeing the invoice. Thanks in advance! | G7: Maria Granja | H7: 46177.634 | I7: white_check_mark | J7: ✅ | K7: @dreimers | L7: @dreimers | M7: 46178.419 | N7: 0 days 18 hrs
A8: https://qualtrics.slack.com/archives/C02KP7NE6FP/p1780635236655159 | B8: 468868 | C8: 12630 | D8: Ariba | E8: PO3286327 | F8: Hi team, can you please try re-uploading the attached invoice to Ariba? The client is encountering an error on their end (screenshot attached). It looks like there was an issue with the file.Can you please advise on how we can troubleshoot this error? Thank you! | G8: Ashley Hudson | H8: 46177.952 | I8: white_check_mark | J8: ✅ | K8: @dreimers | L8: @dreimers | M8: 46197.54 | N8: 19 days 14 hrs
A9: https://qualtrics.slack.com/archives/C02KP7NE6FP/p1780644026629379 | B9: INV00020070 / INV00020071 / INV00020069 / 469136 | C9: See below | D9: Taulia | E9: See below | F9: See replies for PO and amount details. Thank you! | G9: Ashley Hudson | H9: 46178.051 | I9: white_check_mark | J9: ✅ | K9: @dreimers | L9: @dreimers | M9: 46178.564 | N9: 0 days 12 hrs
A10: https://qualtrics.slack.com/archives/C02KP7NE6FP/p1780688144531449 | C10: 8.5K | D10: Ariba | F10: We have an opp we can't process because we are waiting for the PO#. Client said that the PO# is already in Ariba. Can you please look into Ariba and see if there is a PO for that amount ($8500 USD)?. If there is one, can you share it so I can update the PO is SFDC and process the opp? | G10: Pamella Covarrubias | H10: 46178.565 | I10: white_check_mark | J10: ✅ | K10: @edeanda | L10: @dreimers | M10: 46178.607 | N10: 0 days 0 hrs
A11: https://qualtrics.slack.com/archives/C02KP7NE6FP/p1780690569170249 | B11: 466580 | C11: 5198.48 | D11: https://www.vendors.gov.sg/ | E11: 6000241132 | F11: Hello Team, The customer requested for e-invoice via vendors@gov for PO #6000241132 under vendor ID: Y286982. I have attached the guide for e-invoice submission via vendors@gov for your reference | G11: Nikhil Anjikar | H11: 46178.588 | I11: white_check_mark | J11: ✅ | K11: @nanjikar | L11: @dreimers | M11: 46183.649 | N11: 5 days 1 hrs
A12: https://qualtrics.slack.com/archives/C02KP7NE6FP/p1780948263572659 | B12: INV00020293 | C12: Google | D12: Google | E12: 4100794478 | F12: Hi team, can you please upload this invoice? Thanks | G12: Daniela Gomez Viscaino | H12: 46181.576 | I12: white_check_mark | J12: ✅ | K12: @dreimers | L12: @dreimers | M12: 46182.331 | N12: 0 days 18 hrs
A13: https://qualtrics.slack.com/archives/C02KP7NE6FP/p1781116613992809 | B13: unknown | C13: unknown | D13: Coupa | E13: 491884 | F13: Hi team! We received a ticket from the client "Coppel, S.A. de C.V." requesting the following: "Could you help us by uploading the documents so we can continue with the receipt and payment process? Invoice, XML, proof of ownership document, goods receipt form signed by the supplier and the Coppel user department, and the supplementary questionnaire. Regards.." No invoice was attached for reference and the PO# is not linked to any Opp in SFDC. Could you track it in the portal? | G13: Eduardo Rivera | H13: 46183.523 | I13: white_check_mark | J13: ✅ | K13: @dreimers | L13: @dreimers | M13: 46183.612 | N13: 0 days 2 hrs
A14: https://qualtrics.slack.com/archives/C02KP7NE6FP/p1781130261976739 | B14: 470660 | C14: 412500 | D14: Coupa | E14: 8005355996 | F14: Client was setup in Coupa under Procter & Gamble - 0015285300.CL | G14: Jose Novelo | H14: 46183.683 | I14: white_check_mark | J14: ✅ | K14: @dreimers | L14: @dreimers | M14: 46197.545 | N14: 13 days 20 hrs
A15: https://qualtrics.slack.com/archives/C02KP7NE6FP/p1781130682061729 | B15: 470678 | C15: 194850 | D15: Awrostamani Portal | E15: 389168 - 0 | G15: Jose Novelo | H15: 46183.688 | I15: white_check_mark | J15: ✅ | K15: @dreimers | L15: @dreimers | M15: 46185.422 | N15: 1 days 17 hrs
A16: https://qualtrics.slack.com/archives/C02KP7NE6FP/p1781242703251409 | B16: 462239 | D16: Coupa | F16: Hi Team, client has requested we void the second entry here as it is invalid/duplicate. Please access platform and adjust | G16: Saiyon Tanaka | H16: 46184.984 | I16: white_check_mark | J16: ✅ | K16: @dreimers | L16: @dreimers | M16: 46185.489 | N16: 0 days 12 hrs
A17: https://qualtrics.slack.com/archives/C02KP7NE6FP/p1781288921850609 | B17: INV00020633 | C17: 557399.09 | D17: Ariba | E17: 4500318350 | F17: Hi Diego, could you please help me uploading this invoice. Thanks! | G17: Daniela Gomez Viscaino | H17: 46185.519 | I17: white_check_mark | J17: ✅ | K17: @dreimers | L17: @dreimers | M17: 46197.547 | N17: 12 days 0 hrs
A18: https://qualtrics.slack.com/archives/C02KP7NE6FP/p1781514317663729 | B18: #464499 | C18: SGD $35,625.00 | D18: Ariba | E18: n.a. | F18: The invoice uploaded in Ariba was incorrect. Could you please upload the attached invoice. Please attention to liyi_cheong@sats.com.sg as verifier. | G18: Emma Günther | H18: 46188.126 | I18: white_check_mark | J18: ✅ | K18: @alejandram | L18: @dreimers | M18: 46192.575 | N18: 4 days 10 hrs
A19: https://qualtrics.slack.com/archives/C02KP7NE6FP/p1781540763692849 | B19: INV00020140 | C19: 1099.74 | D19: PEPPOL | E19: 26035603 | G19: Fabrizio Rico del Mazo | H19: 46188.434 | I19: white_check_mark | J19: ✅ | K19: @dreimers | L19: @dreimers | M19: 46197.551 | N19: 9 days 2 hrs
A20: https://qualtrics.slack.com/archives/C02KP7NE6FP/p1781559825463709 | B20: INV00020695 | C20: INV00020695 | D20: Ariba | E20: 4100813377 | G20: Daniela Gomez Viscaino | H20: 46188.655 | I20: white_check_mark | J20: ✅ | K20: @aprilj | L20: @aprilj | M20: 46189.315 | N20: 0 days 15 hrs
A21: https://qualtrics.slack.com/archives/C02KP7NE6FP/p1781560246081169 | B21: INV00020722 | C21: 10500 | D21: Ariba | E21: 4100811071 | G21: Daniela Gomez Viscaino | H21: 46188.659 | I21: white_check_mark | J21: ✅ | K21: @aprilj | L21: @aprilj | M21: 46189.318 | N21: 0 days 15 hrs
A22: https://qualtrics.slack.com/archives/C02KP7NE6FP/p1781561118124499 | B22: INV00020373 | C22: 209034 | D22: Coupa | E22: 374271 | G22: Daniela Gomez Viscaino | H22: 46188.67 | I22: white_check_mark | J22: ✅ | K22: @dreimers | L22: @aprilj | M22: 46189.331 | N22: 0 days 15 hrs
A23: https://qualtrics.slack.com/archives/C02KP7NE6FP/p1781625323936489 | B23: 470845 | C23: 28000 | D23: https://suppliers.qf.org.qa/ | E23: QF-PO-46594-HOP | F23: You may now upload the related invoice electronically by using the QF I-Supplier Portal at https://suppliers.qf.org.qa/ In case of any issues during the submission process, kindly contact QF Procurement Relations procurementrelations@qf.org.qa to address your concern. | G23: Fabrizio Rico del Mazo | H23: 46189.413 | I23: white_check_mark | J23: ✅ | K23: @dreimers | L23: @dreimers | M23: 46202.489 | N23: 13 days 1 hrs
A24: https://qualtrics.slack.com/archives/C02KP7NE6FP/p1781634749343139 | B24: INV00020793 | C24: 31752 | D24: Microsoft | E24: 101669908 | G24: Diego Cué Vázquez | H24: 46189.522 | I24: white_check_mark | J24: ✅ | K24: @dreimers | L24: @dreimers | M24: 46190.381 | N24: 0 days 20 hrs
A25: https://qualtrics.slack.com/archives/C02KP7NE6FP/p1781635224453029 | B25: INV00020795 | C25: 32760 | D25: Microsoft | E25: 101626136 | G25: Diego Cué Vázquez | H25: 46189.528 | I25: white_check_mark | J25: ✅ | K25: @dreimers | L25: @dreimers | M25: 46190.38 | N25: 0 days 20 hrs
A26: https://qualtrics.slack.com/archives/C02KP7NE6FP/p1781725717115399 | B26: INV00020920 | C26: 200410 | D26: COUPA | E26: 4614038 | G26: Andrea Juarez | H26: 46190.575 | I26: white_check_mark | J26: ✅ | K26: @dreimers | L26: @dreimers | M26: 46190.583 | N26: 0 days 0 hrs
A27: https://qualtrics.slack.com/archives/C02KP7NE6FP/p1781797607782699 | B27: INV00020933 | C27: 161256.8 | D27: ARIBA | E27: 4520248300 | G27: Andrea Juarez | H27: 46191.407 | I27: white_check_mark | J27: ✅ | K27: @dreimers | L27: @dreimers | M27: 46191.427 | N27: 0 days 0 hrs
A28: https://qualtrics.slack.com/archives/C02KP7NE6FP/p1781804512723809 | B28: 470501 | C28: 2080 | D28: transcepta | E28: BB02012207 | G28: Erika Sorrell | H28: 46191.486 | I28: white_check_mark | J28: ✅ | K28: @aprilj | L28: @aprilj | M28: 46191.562 | N28: 0 days 1 hrs
A29: https://qualtrics.slack.com/archives/C02KP7NE6FP/p1781808178507259 | B29: INV00020607 | C29: 48998 | D29: coupa | E29: 373752 | G29: Alejandro Salazar Copado | H29: 46191.529 | I29: white_check_mark | J29: ✅ | K29: @dreimers | L29: @dreimers | M29: 46191.555 | N29: 0 days 0 hrs
A30: https://qualtrics.slack.com/archives/C02KP7NE6FP/p1781811873820999 | B30: INV00021001 | C30: 27630 | D30: Suppplier connect | E30: 70001688499 | G30: Diego Cué Vázquez | H30: 46191.572 | I30: white_check_mark | J30: ✅ | K30: @dreimers | L30: @dreimers | M30: 46191.607 | N30: 0 days 0 hrs
A31: https://qualtrics.slack.com/archives/C02KP7NE6FP/p1781887412035269 | B31: INV00020899 | C31: 1,768,194.49 USD | D31: Ariba | E31: PO3000364445 | F31: Hi team, can you help me with this upload? thanks | G31: Daniela Gomez Viscaino | H31: 46192.446 | I31: white_check_mark | J31: ✅ | K31: @dreimers | L31: @dreimers | M31: 46197.551 | N31: 5 days 2 hrs
A32: https://qualtrics.slack.com/archives/C02KP7NE6FP/p1781890631636629 | B32: INV00020931 | C32: 63000 | D32: Coupa | E32: 7202278873 | G32: Andrea Juarez | H32: 46192.484 | I32: white_check_mark | J32: ✅ | K32: @dreimers | L32: @dreimers | M32: 46192.532 | N32: 0 days 1 hrs
A33: https://qualtrics.slack.com/archives/C02KP7NE6FP/p1781903380133369 | B33: INV00020933 | C33: 161256.8 | D33: Ariba | E33: 4520248300 | F33: Hi Diego, could you help me with this request please | G33: Daniela Gomez Viscaino | H33: 46192.631 | I33: white_check_mark | J33: ✅ | K33: @dreimers | L33: @dreimers | M33: 46195.41 | N33: 2 days 18 hrs
A34: https://qualtrics.slack.com/archives/C02KP7NE6FP/p1781904191133049 | B34: INV00020931 | C34: 63000 | D34: Coupa | E34: 7202278873 | G34: Daniela Gomez Viscaino | H34: 46192.64 | I34: white_check_mark | J34: ✅ | K34: @dreimers | L34: @dreimers | M34: 46195.422 | N34: 2 days 18 hrs
A35: https://qualtrics.slack.com/archives/C02KP7NE6FP/p1781904352478749 | B35: INV00020793 | C35: 31752 | D35: Microsoft | E35: 101669908 | G35: Daniela Gomez Viscaino | H35: 46192.642 | I35: white_check_mark | J35: ✅ | K35: @dreimers | L35: @dreimers | M35: 46195.443 | N35: 2 days 19 hrs
A36: https://qualtrics.slack.com/archives/C02KP7NE6FP/p1781904683647979 | B36: INV00020920 | C36: 200410 | D36: Coupa | E36: 4614038 | G36: Daniela Gomez Viscaino | H36: 46192.646 | I36: white_check_mark | J36: ✅ | K36: @dreimers | L36: @dreimers | M36: 46195.426 | N36: 2 days 18 hrs
A37: https://qualtrics.slack.com/archives/C02KP7NE6FP/p1781906633040689 | B37: INV00020867 | C37: 20000 | D37: Ariba | E37: 4100803422 | G37: Daniela Gomez Viscaino | H37: 46192.668 | I37: white_check_mark | J37: ✅ | K37: @dreimers | L37: @dreimers | M37: 46195.434 | N37: 2 days 18 hrs
A38: https://qualtrics.slack.com/archives/C02KP7NE6FP/p1782136417315069 | B38: QILNEW2100 | C38: 4815.72 | D38: Chorus Pro | E38: 1513730710 | F38: Hi, the client accidentally deleted the request of upload, could we please reuload the invoice (PO attached) | G38: Yulian Trishch | H38: 46195.326 | I38: white_check_mark | J38: ✅ | K38: @dreimers | L38: @dreimers | M38: 46195.449 | N38: 0 days 2 hrs
A39: https://qualtrics.slack.com/archives/C02KP7NE6FP/p1782240292382289 | B39: INV00020373 | C39: JPY 209,034 | D39: Coupa | E39: 376864 | F39: Please find attached the manually updated invoice with the new PO number requested by the customer. Per Daiki's instructions, please re-upload it to Coupa. Thank you. | G39: Alejandro Salazar Copado | H39: 46196.529 | I39: white_check_mark | J39: ✅ | K39: @dreimers | L39: @dreimers | M39: 46196.544 | N39: 0 days 0 hrs
A40: https://qualtrics.slack.com/archives/C02KP7NE6FP/p1782245205033039 | B40: INV00021485 | C40: 16575 | D40: Ariba | E40: PO2339695 | G40: Daniela Gomez Viscaino | H40: 46196.586 | I40: white_check_mark | J40: ✅ | K40: @dreimers | L40: @dreimers | M40: 46220.591 | N40: 24 days 0 hrs
A41: https://qualtrics.slack.com/archives/C02KP7NE6FP/p1782245276523869 | B41: INV00021506 | C41: 8287.5 | D41: Ariba | E41: PO2339695 | G41: Daniela Gomez Viscaino | H41: 46196.588 | I41: white_check_mark | J41: ✅ | K41: @dreimers | L41: @dreimers | M41: 46197.455 | N41: 0 days 20 hrs
A42: https://qualtrics.slack.com/archives/C02KP7NE6FP/p1782247415846169 | B42: INV00020795 | C42: 32760 | D42: Microsoft | E42: 101626136 | F42: Hi team, could you please help me with this upload? Thanks | G42: Daniela Gomez Viscaino | H42: 46196.613 | I42: white_check_mark | J42: ✅ | K42: @dreimers | L42: @dreimers | M42: 46197.462 | N42: 0 days 20 hrs
A43: https://qualtrics.slack.com/archives/C02KP7NE6FP/p1782247984010569 | B43: INV00021546 | C43: 46200 | D43: Coupa | E43: 1000411093 | G43: Daniela Gomez Viscaino | H43: 46196.62 | I43: white_check_mark | J43: ✅ | K43: @dreimers | L43: @dreimers | M43: 46197.461 | N43: 0 days 20 hrs
A44: https://qualtrics.slack.com/archives/C02KP7NE6FP/p1782248532343589 | B44: INV00021437 | C44: 27630 | D44: Supplier Connect | E44: 70001688499 | G44: Daniela Gomez Viscaino | H44: 46196.626 | I44: white_check_mark | J44: ✅ | K44: @dreimers | L44: @dreimers | M44: 46197.475 | N44: 0 days 20 hrs
A45: https://qualtrics.slack.com/archives/C02KP7NE6FP/p1782405536016509 | B45: #Q-333765 | C45: 13230 | D45: Oracle Cloud: https://idcs-50547f153a4d499aa070617fc8660e66.identity.oraclecloud.com/ui/v1/signin | F45: Hi team, the client has requested that we upload the quote (attached) to the platform, is this something you can assist with? ODO ticket for reference: https://odo.corp.qualtrics.com/?TopNav=Tickets&a=Tickets&b=TicketViewer&tid=ZZ_8A6570E094164A57 | G45: Andres Prieto | H45: 46198.441 | I45: white_check_mark | J45: ✅ | K45: @dreimers | L45: @dreimers | M45: 46198.568 | N45: 0 days 3 hrs
A46: https://qualtrics.slack.com/archives/C02KP7NE6FP/p1782408468202609 | B46: INV00021651 | C46: 185445.16 | D46: Coupa | E46: 8006659809 | F46: Hi Diego, coould you please help me with this upload? Thanks | G46: Daniela Gomez Viscaino | H46: 46198.476 | I46: white_check_mark | J46: ✅ | K46: @dreimers | L46: @dreimers | M46: 46198.591 | N46: 0 days 2 hrs
A47: https://qualtrics.slack.com/archives/C02KP7NE6FP/p1782409635089989 | B47: INV00021650 | C47: 42,028.13 USD | D47: Coupa | E47: 8006643124 | F47: Hi team, could you please help us sibmut this invoice?thank you! | G47: Maria de Lourdes López Núñez | H47: 46198.49 | I47: white_check_mark | J47: ✅ | K47: @alejandram | L47: @dreimers | M47: 46198.574 | N47: 0 days 2 hrs
A48: https://qualtrics.slack.com/archives/C02KP7NE6FP/p1782467984873559 | B48: 470840 | C48: EUR €5,000.00 | D48: Chorus Pro (http://chorus-pro.gouv.fr) | E48: 4500474677 | F48: Hello Team, Please kindly upload the invoice on the above mentioned portal. | G48: Kaushal Hogade | H48: 46199.163 | I48: white_check_mark | J48: ✅ | K48: @dreimers | M48: 46199.471 | N48: 0 days 7 hrs
A49: https://qualtrics.slack.com/archives/C02KP7NE6FP/p1782490445440069 | B49: 2D-21801766 | C49: 45000 | D49: coupa | E49: 2D-21801766 | F49: HEllo team, Amazon sent the PO 2D-21801766 and I want to ensure that we map it appropietly, can you help us map it? | G49: Imanol Martinez | H49: 46199.426 | I49: white_check_mark | J49: ✅ | K49: @alejandram | L49: @dreimers | M49: 46199.488 | N49: 0 days 1 hrs
A50: https://qualtrics.slack.com/archives/C02KP7NE6FP/p1782708717318919 | B50: INV00021939 | C50: 63000 | D50: MSFT Portal | E50: 101633045 | G50: Andrea Juarez | H50: 46201.952 | I50: white_check_mark | J50: ✅ | K50: @dreimers | L50: @dreimers | M50: 46202.547 | N50: 0 days 14 hrs
A51: https://qualtrics.slack.com/archives/C02KP7NE6FP/p1782751258450949 | B51: 4500114905 | C51: 4.091,04 | D51: https://portail.chorus-pro.gouv.fr/aife_csm | E51: 4500114905 | F51: URGENT ! The client funds are expiring and they need to receive via chorus pro the invoice before the end of tomorrow. could you please support me? Please find here the opportunity on sfdc: https://qualtrics.lightning.force.com/lightning/r/Opportunity/006UJ00000pjaefYAA/view | G51: Eleonora Amarante | H51: 46202.438 | I51: white_check_mark | J51: ✅ | K51: @dreimers | L51: @dreimers | M51: 46202.518 | N51: 0 days 1 hrs
A52: https://qualtrics.slack.com/archives/C02KP7NE6FP/p1782757390879829 | B52: 471109 | C52: 40825.37 | D52: Coupa | E52: 1000059569 | G52: Fabrizio Rico del Mazo | H52: 46202.515 | I52: white_check_mark | J52: ✅ | K52: @kburkett | L52: @kburkett | M52: 46202.621 | N52: 0 days 2 hrs
A53: https://qualtrics.slack.com/archives/C02KP7NE6FP/p1782780784921059 | B53: INV00021802 | C53: 12499.86 | D53: Ariba | E53: PO3296526 | F53: Hi Diego, could you please help me uploading this invoice? Thanks! | G53: Daniela Gomez Viscaino | H53: 46202.786 | I53: white_check_mark | J53: ✅ | K53: @kburkett | L53: @kburkett | M53: 46202.937 | N53: 0 days 3 hrs
A54: https://qualtrics.slack.com/archives/C02KP7NE6FP/p1782780921500509 | B54: INV00021701 | C54: 120625 | D54: Coupa | E54: #PHKL212543 | G54: Daniela Gomez Viscaino | H54: 46202.788 | I54: white_check_mark | J54: ✅ | K54: @kburkett | L54: @kburkett | M54: 46202.917 | N54: 0 days 3 hrs
A55: https://qualtrics.slack.com/archives/C02KP7NE6FP/p1782781161875839 | B55: INV00021462 | C55: 41862.5 | D55: Ariba | E55: 4100799459 | G55: Daniela Gomez Viscaino | H55: 46202.791 | I55: white_check_mark | J55: ✅ | K55: @kburkett | L55: @kburkett | M55: 46202.933 | N55: 0 days 3 hrs
A56: https://qualtrics.slack.com/archives/C02KP7NE6FP/p1782781233677379 | B56: INV00021491 | C56: 8752.5 | D56: Coupa | E56: WAYPO3409 | G56: Daniela Gomez Viscaino | H56: 46202.792 | I56: white_check_mark | J56: ✅ | K56: @kburkett | L56: @kburkett | M56: 46202.929 | N56: 0 days 3 hrs
A57: https://qualtrics.slack.com/archives/C02KP7NE6FP/p1782781400902979 | B57: INV00021769 | C57: 58439.39 | D57: Coupa | E57: 5200375249 | G57: Daniela Gomez Viscaino | H57: 46202.794 | I57: white_check_mark | J57: ✅ | K57: @alejandram | L57: @kburkett | M57: 46210.341 | N57: 7 days 13 hrs
A58: https://qualtrics.slack.com/archives/C02KP7NE6FP/p1782783951045149 | B58: INV00021673 | C58: 135000 | D58: Taulia | E58: 8350154679 | F58: Hi team, can you please confirm if this has already been uploaded and if not, can you please uploade this ASAP? This is a part of an executive escalation in APJ ANZ. Thank you! | G58: Ashley Hudson | H58: 46202.822 | I58: white_check_mark | J58: ✅ | K58: @kburkett | L58: @kburkett | M58: 46202.9 | N58: 0 days 1 hrs
A59: https://qualtrics.slack.com/archives/C02KP7NE6FP/p1782839197642209 | B59: INV00022143 | C59: 8287.5 | D59: ariba | E59: PO2339695 | F59: Hi team, your help with the upload of this customer. Thanks! | G59: Daniela Gomez Viscaino | H59: 46203.462 | I59: white_check_mark | J59: ✅ | K59: @dreimers | L59: @dreimers | M59: 46218.473 | N59: 15 days 0 hrs
A60: https://qualtrics.slack.com/archives/C02KP7NE6FP/p1782848673192709 | B60: INV00019962 | C60: 68750 | D60: Ariba | F60: Can we please set up a note so ALL invoices for UHG are send to Ariba? | G60: Elías Chávez Zamorano | H60: 46203.552 | I60: white_check_mark | J60: ✅ | K60: @dreimers | L60: @dreimers | M60: 46204.506 | N60: 0 days 22 hrs
A61: https://qualtrics.slack.com/archives/C02KP7NE6FP/p1782920703110419 | B61: INV00021682 | C61: 470000 | D61: Ariba | E61: C14345 | F61: Hi team, could you please upload this invoice to the portal? Thanks! | G61: Daniela Gomez Viscaino | H61: 46204.406 | I61: white_check_mark | J61: ✅ | K61: @aprilj | L61: @aprilj | M61: 46204.423 | N61: 0 days 0 hrs
A62: https://qualtrics.slack.com/archives/C02KP7NE6FP/p1782921476713909 | B62: 471137 | C62: 14943.64 | D62: Option 1: (Preferred - Via Peppol): * Peppol ID: 9938:lu19805732 (connecting through an access point) Option 2 (Alternative): Via the free portal MyGuichet.lu | E62: n/s | G62: Yulian Trishch | H62: 46204.412 | I62: white_check_mark | J62: ✅ | K62: @dreimers | L62: @dreimers | M62: 46209.486 | N62: 5 days 1 hrs
A63: https://qualtrics.slack.com/archives/C02KP7NE6FP/p1782937304716389 | B63: 467590 | C63: 60000 | D63: Ariba | E63: 4100819224 | F63: Google invoice, please upload without taxes (if applicable). | G63: Abril Marmolejo Portillo | H63: 46204.598 | I63: white_check_mark | J63: ✅ | K63: @dreimers | L63: @dreimers | M63: 46204.618 | N63: 0 days 0 hrs
A64: https://qualtrics.slack.com/archives/C02KP7NE6FP/p1782939564767019 | B64: INV00022317 | C64: 11940.75 | D64: Ariba | E64: 4100809710 | G64: Andrea Juarez | H64: 46204.624 | I64: white_check_mark | J64: ✅ | K64: @dreimers | L64: @dreimers | M64: 46205.412 | N64: 0 days 18 hrs
A65: https://qualtrics.slack.com/archives/C02KP7NE6FP/p1783021662463589 | B65: 471148 | C65: 5644049 | D65: Ariba | E65: 4571069 | G65: Jose Novelo | H65: 46205.574 | I65: white_check_mark | J65: ✅ | K65: @dreimers | L65: @dreimers | M65: 46206.399 | N65: 0 days 19 hrs
A66: https://qualtrics.slack.com/archives/C02KP7NE6FP/p1783029669135139 | B66: 465913 | C66: 11839.75 | D66: Coupa | E66: C000159264 | F66: This PO covers $6,000 of the invoice | G66: Fernando Anaya | H66: 46205.663 | I66: white_check_mark | J66: ✅ | K66: @dreimers | L66: @dreimers | M66: 46206.446 | N66: 0 days 18 hrs
A67: https://qualtrics.slack.com/archives/C02KP7NE6FP/p1783095362693999 | B67: 471232 | C67: 30995.01 | D67: Ariba | E67: 4100733205 | G67: Fabrizio Rico del Mazo | H67: 46206.427 | I67: white_check_mark | J67: ✅ | K67: @dreimers | L67: @dreimers | M67: 46206.447 | N67: 0 days 0 hrs
A68: https://qualtrics.slack.com/archives/C02KP7NE6FP/p1783096056684209 | B68: 471234 | C68: 34884 | D68: Ariba | E68: 4300058098 | G68: Fabrizio Rico del Mazo | H68: 46206.435 | I68: white_check_mark | J68: ✅ | K68: @dreimers | L68: @dreimers | M68: 46206.452 | N68: 0 days 0 hrs
A69: https://qualtrics.slack.com/archives/C02KP7NE6FP/p1783096121469759 | B69: 471235 | C69: 17748 | D69: Ariba | E69: 4300058098 | G69: Fabrizio Rico del Mazo | H69: 46206.436 | I69: white_check_mark | J69: ✅ | K69: @dreimers | L69: @dreimers | M69: 46206.514 | N69: 0 days 1 hrs
A70: https://qualtrics.slack.com/archives/C02KP7NE6FP/p1783096225477409 | B70: 471236 | C70: 8568 | D70: Ariba | E70: 4300058098 | F70: AR | G70: Fabrizio Rico del Mazo | H70: 46206.437 | I70: white_check_mark | J70: ✅ | K70: @dreimers | L70: @dreimers | M70: 46245.388 | N70: 38 days 22 hrs
A71: https://qualtrics.slack.com/archives/C02KP7NE6FP/p1783323228536079 | B71: 464416 | C71: 400000 | D71: https://aof16igsa.accounts.ondemand.com/oauth2/authorize?client_id=a6b877e0-3b0e-468f-95a2-71da64eb729c&response_type=code&redirect_uri=https%3A%2F%2Fpihprod.authentication.eu10.hana.ondemand.com%2Flogin%2Fcallback%2Fhttpsaof16igsa.accounts.ondemand.com&state=QNU4Mo8xi7&code_challenge=bQH2TO14-IIbsadIzDWlvNxrRLXLqzXjCjNYxcRgP7w&code_challenge_method=S256&scope=email+openid+profile&nonce=c82THVKsG_2V | E71: confused as to what to put in the PO number (please see attached) | F71: ticket reference : https://odo.corp.qualtrics.com/?TopNav=Tickets&b=TicketViewer&tid=ZZ_EDE60075E8464F77 | G71: Bhumika Kokate | H71: 46209.063 | I71: white_check_mark | J71: ✅ | K71: @dreimers | L71: @dreimers | M71: 46209.465 | N71: 0 days 9 hrs
A72: https://qualtrics.slack.com/archives/C02KP7NE6FP/p1783349844911569 | B72: 470826 | C72: 5762.41 | D72: Chorus Pro | E72: 1) 4500449836 2) 4500449278 | F72: Hi Team, could you please upload invoice 470826 to the Chorus Pro portal? There must be two PO numbers bc of the customer's internal requirements; I'm attaching the PO's in question to the workflow. Thank you! | G72: Gabriela Kwaśniewska | H72: 46209.37 | I72: white_check_mark | J72: ✅ | K72: @dreimers | L72: @dreimers | M72: 46209.461 | N72: 0 days 2 hrs
A73: https://qualtrics.slack.com/archives/C02KP7NE6FP/p1783537689819299 | B73: 433710 | C73: 9536.95 | D73: Coupa | E73: C000159264 | G73: Fernando Anaya | H73: 46211.547 | I73: white_check_mark | J73: ✅ | K73: @dreimers | L73: @dreimers | M73: 46231.498 | N73: 19 days 22 hrs
A74: https://qualtrics.slack.com/archives/C02KP7NE6FP/p1783537889016149 | B74: 465913 | C74: 11839.75 | D74: Coupa | E74: C000338202 | G74: Fernando Anaya | H74: 46211.549 | I74: white_check_mark | J74: ✅ | K74: @dreimers | L74: @dreimers | M74: 46231.499 | N74: 19 days 22 hrs
A75: https://qualtrics.slack.com/archives/C02KP7NE6FP/p1783538118203689 | B75: INV00022719 | C75: $103,151.04 USD | D75: Coupa | E75: EMINC030671 | F75: This is a manual invoice approved by Tristan Carlisle - Deloitte is fixing the zuora contract as it is splitting the invoice in 2 different PDFs. Any concerns, please let me know. Thank you! | G75: Maria de Lourdes López Núñez | H75: 46211.551 | I75: white_check_mark | J75: ✅ | K75: @dreimers | L75: @dreimers | M75: 46211.601 | N75: 0 days 1 hrs
A76: https://qualtrics.slack.com/archives/C02KP7NE6FP/p1783540660113399 | B76: INV00022892 | C76: 18950 | D76: ARIBA | E76: 4100821392 | G76: Andrea Juarez | H76: 46211.581 | I76: white_check_mark | J76: ✅ | K76: @dreimers | L76: @dreimers | M76: 46211.613 | N76: 0 days 0 hrs
A77: https://qualtrics.slack.com/archives/C02KP7NE6FP/p1783540692181239 | B77: INV00022324 | C77: 65832.39 | D77: Ariba | E77: 4504632525 | G77: Daniela Gomez Viscaino | H77: 46211.582 | I77: white_check_mark | J77: ✅ | K77: @dreimers | L77: @dreimers | M77: 46211.615 | N77: 0 days 0 hrs
A78: https://qualtrics.slack.com/archives/C02KP7NE6FP/p1783600241295799 | B78: 470840 | C78: EUR 5000 | D78: Chorus Pro | E78: 4500497963 | G78: Gabriela Kwaśniewska | H78: 46212.271 | I78: white_check_mark | J78: ✅ | K78: @dreimers | L78: @dreimers | M78: 46212.484 | N78: 0 days 5 hrs
A79: https://qualtrics.slack.com/archives/C02KP7NE6FP/p1783659623608169 | B79: 465391 | C79: 26547.11 | D79: Ariba | E79: PO3303110 | G79: George Kahy | H79: 46212.958 | I79: white_check_mark | J79: ✅ | K79: @dreimers | L79: @dreimers | M79: 46213.498 | N79: 0 days 12 hrs
A80: https://qualtrics.slack.com/archives/C02KP7NE6FP/p1783720549721079 | F80: Hi team, we received an automatic notification stating that the Electronic Invoicing Reform (RFE) will come into effect on September 1, 2026, for large enterprises and mid-cap companies (ETI), and on September 1, 2027, for SMEs. It mandates electronic invoicing via an Approved Platform (Plateforme Agréée - PA) for all invoices addressed to TDF SAS (SIREN 342404399). I am attaching the file that came with the email, just thought you would want the heads up, not sure if there is anything that needs to be done. The Account in SFDC is T D F. | G80: Andres Prieto | H80: 46213.661 | I80: white_check_mark | J80: ✅ | K80: @dreimers | L80: @dreimers | M80: 46216.506 | N80: 2 days 20 hrs
A81: https://qualtrics.slack.com/archives/C02KP7NE6FP/p1783722187403289 | B81: 471288 | C81: INR 6,254,388.00 | D81: Ariba | E81: 9200085142 | G81: Alejandro Salazar Copado | H81: 46213.682 | I81: white_check_mark | J81: ✅ | K81: @dreimers | L81: @dreimers | M81: 46216.509 | N81: 2 days 19 hrs
A82: https://qualtrics.slack.com/archives/C02KP7NE6FP/p1783956955494869 | B82: 471302 | C82: 393466.13 | D82: Ariba | E82: BD81091 | G82: Alejandro Salazar Copado | H82: 46216.4 | I82: white_check_mark | J82: ✅ | K82: @dreimers | L82: @dreimers | M82: 46218.468 | N82: 2 days 1 hrs
A83: https://qualtrics.slack.com/archives/C02KP7NE6FP/p1783962749437319 | B83: 471289 | C83: 800000 | D83: Ariba - McDonald's | E83: P O U S 0 0 1 0 0 0 0 0 0 9 1 7 | F83: McDonald's | G83: Karla Tellez | H83: 46216.464 | I83: white_check_mark | J83: ✅ | K83: @dreimers | L83: @dreimers | M83: 46216.515 | N83: 0 days 1 hrs
A84: https://qualtrics.slack.com/archives/C02KP7NE6FP/p1783974051159589 | B84: INV00023439 | C84: 776740 | D84: Coupa | E84: POC212559 | F84: upload in Coupa under KPMG LLP - QUALTRICS LLC (1000034721) | G84: Cindy Espinola | H84: 46216.597 | I84: white_check_mark | J84: ✅ | K84: @dreimers | L84: @dreimers | M84: 46216.602 | N84: 0 days 0 hrs
A85: https://qualtrics.slack.com/archives/C02KP7NE6FP/p1784007289327999 | B85: INV00020373 | C85: 209034 | D85: Coupa | E85: 376864 | G85: Daiki Hayashi | H85: 46216.982 | I85: white_check_mark | J85: ✅ | K85: @dreimers | L85: @dreimers | M85: 46218.468 | N85: 1 days 11 hrs
A86: https://qualtrics.slack.com/archives/C02KP7NE6FP/p1784042880474209 | B86: INV00022437 | C86: GBP 224,999.00 | D86: Ariba | F86: Hi team, we need to register the Ariba customer Portal. Thanks! Link https://portal.us.bn.cloud.ariba.com/onboarding/portal/nextgen#/landinghere | G86: Mariana Senkovych | H86: 46217.392 | I86: white_check_mark | J86: ✅ | K86: @dreimers | L86: @dreimers | M86: 46218.552 | N86: 1 days 3 hrs
A87: https://qualtrics.slack.com/archives/C02KP7NE6FP/p1784047732512439 | B87: 377444 | C87: 29063.99 | D87: https://www.roshn.sa/en/opportunities | E87: PO-RRE23124 | F87: she sd the invoice needs to be uploaded online through their portal... roshn.sa .....click opportunities.... scroll down to vendor section and click new registrations and client needs to register and upload invoice. | G87: Nathan Smith | H87: 46217.45 | I87: white_check_mark | J87: ✅ | K87: @dreimers | L87: @dreimers | M87: 46245.381 | N87: 27 days 22 hrs
A88: https://qualtrics.slack.com/archives/C02KP7NE6FP/p1784225706072839 | B88: INV00023643 | C88: 810 | D88: Google | E88: 4100816298 | G88: Diego Cué Vázquez | H88: 46219.51 | I88: white_check_mark | J88: ✅ | K88: @dreimers | L88: @dreimers | M88: 46219.591 | N88: 0 days 1 hrs
A89: https://qualtrics.slack.com/archives/C02KP7NE6FP/p1784231709730789 | B89: 468661 | C89: 29380 | D89: Vendor Invoice Management Portal (Pipefy) | E89: 2001786443 | F89: Hi team! Got this message from the customer: https://odo.corp.qualtrics.com/?TopNav=Tickets&a=Tickets&b=TicketViewer&tid=ZZ_C523CF7E5BE94E18 | G89: Erick Z. Cabrera | H89: 46219.579 | I89: white_check_mark | J89: ✅ | K89: @dreimers | L89: @dreimers | M89: 46223.593 | N89: 4 days 0 hrs
A90: https://qualtrics.slack.com/archives/C02KP7NE6FP/p1784319620012709 | B90: INV00023799 | C90: 421200 | D90: Tungsten | E90: Non PO, could you please try to find it? Thank you! | G90: Cindy Espinola | H90: 46220.596 | I90: white_check_mark | J90: ✅ | K90: @dreimers | L90: @dreimers | M90: 46223.593 | N90: 2 days 23 hrs
A91: https://qualtrics.slack.com/archives/C02KP7NE6FP/p1784576994260589 | B91: INV00020544 | C91: 3398.16 | D91: Coupa | E91: SG1011000477800 | F91: Hello Team, I have received the instruction to submit invoice to Coupa mailbox: invoices+singapore_ops@aon.coupahost.com | G91: Nikhil Anjikar | H91: 46223.573 | I91: white_check_mark | J91: ✅ | K91: @dreimers | L91: @dreimers | M91: 46223.596 | N91: 0 days 0 hrs
A92: https://qualtrics.slack.com/archives/C02KP7NE6FP/p1784630293893669 | B92: INV00023799 | C92: 421 200,00 € | D92: Tradeshift | E92: PO17883029. | F92: Hi all, I have added the PO to Zuora and made notes as for portal upload. Not sure if sb reads the comments so I decided to create a portal request here as well. | G92: Mariana Senkovych | H92: 46224.192 | I92: white_check_mark | J92: ✅ | K92: @dreimers | L92: @dreimers | M92: 46224.448 | N92: 0 days 6 hrs
A93: https://qualtrics.slack.com/archives/C02KP7NE6FP/p1784647599706229 | B93: INV00022435 | C93: 307677.27 | D93: Sesami | F93: Hello team, can you make sure invoice is submitted to their portal (sesami) | G93: Mariano Muniain | H93: 46224.392 | I93: white_check_mark | J93: ✅ | K93: @eparedes | L93: @dreimers | M93: 46224.536 | N93: 0 days 3 hrs
A94: https://qualtrics.slack.com/archives/C02KP7NE6FP/p1784650553741169 | B94: INV00023491 | C94: 40000 | D94: Easy platform | G94: Fabrizio Rico del Mazo | H94: 46224.427 | I94: white_check_mark | J94: ✅ | K94: @dreimers | L94: @dreimers | M94: 46224.469 | N94: 0 days 1 hrs
A95: https://qualtrics.slack.com/archives/C02KP7NE6FP/p1784743433231479 | B95: 4 6 5 3 6 9 | C95: 2100 | D95: Transcepta | E95: B 0 0 3 2 5 5 5 8 6 | F95: Hi team! Can you pls help us upload the invoice to their portal? Thanks! | G95: Aity Sánchez Sandoval | H95: 46225.502 | I95: white_check_mark | J95: ✅ | K95: @dreimers | L95: @dreimers | M95: 46226.395 | N95: 0 days 21 hrs
A96: https://qualtrics.slack.com/archives/C02KP7NE6FP/p1784743819778489 | B96: INV00023728 | C96: 5600 | D96: University of Pennsylvania's dedicated supplier/vendor portal. | F96: Customer cannot process payment because Penn’s supplier portal still lists Qualtrics’ corporate address (333 W River Park Drive, Provo UT 84604) as the payment address, while the invoice states not to send payment there. Please update Qualtrics’ remittance/payment address in the customer supplier portal/vendor profile so the invoice can be paid. | G96: Aity Sánchez Sandoval | H96: 46225.506 | I96: white_check_mark | J96: ✅ | K96: @dreimers | L96: @dreimers | M96: 46225.562 | N96: 0 days 1 hrs
A97: https://qualtrics.slack.com/archives/C02KP7NE6FP/p1784766611937409 | B97: INV00023950 | C97: 84000 | D97: Coupa | E97: 35931 | G97: Cindy Espinola | H97: 46225.768 | I97: white_check_mark | J97: ✅ | K97: @dreimers | L97: @dreimers | M97: 46226.4 | N97: 0 days 15 hrs
A98: https://qualtrics.slack.com/archives/C02KP7NE6FP/p1784826631368629 | B98: INV00023865 | C98: 155840 | D98: Microsoft | E98: I don't have the PO# | G98: Diego Cué Vázquez | H98: 46226.465 | I98: white_check_mark | J98: ✅ | K98: @alejandram | L98: @dreimers | M98: 46227.346 | N98: 0 days 21 hrs
A99: https://qualtrics.slack.com/archives/C02KP7NE6FP/p1784826671718129 | B99: INV00023868 | C99: 119104.88 | D99: Ariba | E99: not needed need to submit to ariba | G99: Diego Cué Vázquez | H99: 46226.466 | I99: white_check_mark | J99: ✅ | K99: @dreimers | L99: @dreimers | M99: 46245.384 | N99: 18 days 22 hrs
A100: https://qualtrics.slack.com/archives/C02KP7NE6FP/p1784842112506619 | B100: INV00020620 | C100: 91878 | D100: Ariba | E100: 8200005584 | G100: Fabrizio Rico del Mazo | H100: 46226.644 | I100: white_check_mark | J100: ✅ | K100: @dreimers | L100: @dreimers | M100: 46227.43 | N100: 0 days 18 hrs
...

Sheet Nomenclature
A1: Emoji | B1: Meaning
A2: 👀 | B2: Pending review
A3: 🔥 | B3: Priority (>100K)
A4: ❓ | B4: Waiting for info
A5: ✅ | B5: Completed

Sheet Datos (calculo)
A1: Invoice Number | B1: Submitted By | C1: Collector assigned | D1: Submit Timestamp | E1: Resolved Timestamp | F1: Resolution (hrs) | G1: Resolution (dias) | H1: Mes | I1: Portal (norm.)
A2: test | B2: Alejandra Mendoza | D2: 46013.894 | H2: 2025-12 | I2: Sin dato
A3: QILNEW1915 | B3: Alejandra Mendoza | C3: @dreimers | D3: 46175.574 | E3: 46176.467 | F3: 21.4 | G3: 0.9 | H3: 2026-06 | I3: Bmw Portal
A4: INV00020111 | B4: Daniela Gomez Viscaino | C4: @dreimers | D4: 46176.435 | E4: 46176.566 | F4: 3.1 | G4: 0.1 | H4: 2026-06 | I4: Ariba
A5: Not Generated | B5: Kaushal Hogade | C5: @dreimers | D5: 46176.463 | E5: 46177.526 | F5: 25.5 | G5: 1.1 | H5: 2026-06 | I5: Chorus Pro
A6: INV00019964 | B6: Daniela Gomez Viscaino | C6: @dreimers | D6: 46176.569 | E6: 46177.513 | F6: 22.7 | G6: 0.9 | H6: 2026-06 | I6: Coupa
A7: 469020 | B7: Maria Granja | C7: @dreimers | D7: 46177.634 | E7: 46178.419 | F7: 18.8 | G7: 0.8 | H7: 2026-06 | I7: Ariba
A8: 468868 | B8: Ashley Hudson | C8: @dreimers | D8: 46177.952 | E8: 46197.54 | F8: 470.1 | G8: 19.6 | H8: 2026-06 | I8: Ariba
A9: INV00020070 / INV00020071 / INV00020069 / 469136 | B9: Ashley Hudson | C9: @dreimers | D9: 46178.051 | E9: 46178.564 | F9: 12.3 | G9: 0.5 | H9: 2026-06 | I9: Taulia
B10: Pamella Covarrubias | C10: @dreimers | D10: 46178.565 | E10: 46178.607 | F10: 1 | G10: 0 | H10: 2026-06 | I10: Ariba
A11: 466580 | B11: Nikhil Anjikar | C11: @dreimers | D11: 46178.588 | E11: 46183.649 | F11: 121.5 | G11: 5.1 | H11: 2026-06 | I11: Portal por URL
A12: INV00020293 | B12: Daniela Gomez Viscaino | C12: @dreimers | D12: 46181.576 | E12: 46182.331 | F12: 18.1 | G12: 0.8 | H12: 2026-06 | I12: Google
A13: unknown | B13: Eduardo Rivera | C13: @dreimers | D13: 46183.523 | E13: 46183.612 | F13: 2.1 | G13: 0.1 | H13: 2026-06 | I13: Coupa
A14: 470660 | B14: Jose Novelo | C14: @dreimers | D14: 46183.683 | E14: 46197.545 | F14: 332.7 | G14: 13.9 | H14: 2026-06 | I14: Coupa
A15: 470678 | B15: Jose Novelo | C15: @dreimers | D15: 46183.688 | E15: 46185.422 | F15: 41.6 | G15: 1.7 | H15: 2026-06 | I15: Awrostamani Portal
A16: 462239 | B16: Saiyon Tanaka | C16: @dreimers | D16: 46184.984 | E16: 46185.489 | F16: 12.1 | G16: 0.5 | H16: 2026-06 | I16: Coupa
A17: INV00020633 | B17: Daniela Gomez Viscaino | C17: @dreimers | D17: 46185.519 | E17: 46197.547 | F17: 288.7 | G17: 12 | H17: 2026-06 | I17: Ariba
A18: #464499 | B18: Emma Günther | C18: @dreimers | D18: 46188.126 | E18: 46192.575 | F18: 106.8 | G18: 4.4 | H18: 2026-06 | I18: Ariba
A19: INV00020140 | B19: Fabrizio Rico del Mazo | C19: @dreimers | D19: 46188.434 | E19: 46197.551 | F19: 218.8 | G19: 9.1 | H19: 2026-06 | I19: Peppol
A20: INV00020695 | B20: Daniela Gomez Viscaino | C20: @aprilj | D20: 46188.655 | E20: 46189.315 | F20: 15.9 | G20: 0.7 | H20: 2026-06 | I20: Ariba
A21: INV00020722 | B21: Daniela Gomez Viscaino | C21: @aprilj | D21: 46188.659 | E21: 46189.318 | F21: 15.8 | G21: 0.7 | H21: 2026-06 | I21: Ariba
A22: INV00020373 | B22: Daniela Gomez Viscaino | C22: @aprilj | D22: 46188.67 | E22: 46189.331 | F22: 15.9 | G22: 0.7 | H22: 2026-06 | I22: Coupa
... A47: INV00021650 | B47: Maria de Lourdes López Núñez | C47: @dreimers | D47: 46198.49 | E47: 46198.574 | F47: 2 | G47: 0.1 | H47: 2026-06 | I47: Coupa
A48: 470840 | B48: Kaushal Hogade | D48: 46199.163 | E48: 46199.471 | F48: 7.4 | G48: 0.3 | H48: 2026-06 | I48: Chorus Pro
A49: 2D-21801766 | B49: Imanol Martinez | C49: @dreimers | D49: 46199.426 | E49: 46199.488 | F49: 1.5 | G49: 0.1 | H49: 2026-06 | I49: Coupa
A50: INV00021939 | B50: Andrea Juarez | C50: @dreimers | D50: 46201.952 | E50: 46202.547 | F50: 14.3 | G50: 0.6 | H50: 2026-06 | I50: Microsoft
A51: 4500114905 | B51: Eleonora Amarante | C51: @dreimers | D51: 46202.438 | E51: 46202.518 | F51: 1.9 | G51: 0.1 | H51: 2026-06 | I51: Chorus Pro
A52: 471109 | B52: Fabrizio Rico del Mazo | C52: @kburkett | D52: 46202.515 | E52: 46202.621 | F52: 2.5 | G52: 0.1 | H52: 2026-06 | I52: Coupa
A53: INV00021802 | B53: Daniela Gomez Viscaino | C53: @kburkett | D53: 46202.786 | E53: 46202.937 | F53: 3.6 | G53: 0.2 | H53: 2026-06 | I53: Ariba
A54: INV00021701 | B54: Daniela Gomez Viscaino | C54: @kburkett | D54: 46202.788 | E54: 46202.917 | F54: 3.1 | G54: 0.1 | H54: 2026-06 | I54: Coupa
A55: INV00021462 | B55: Daniela Gomez Viscaino | C55: @kburkett | D55: 46202.791 | E55: 46202.933 | F55: 3.4 | G55: 0.1 | H55: 2026-06 | I55: Ariba
A56: INV00021491 | B56: Daniela Gomez Viscaino | C56: @kburkett | D56: 46202.792 | E56: 46202.929 | F56: 3.3 | G56: 0.1 | H56: 2026-06 | I56: Coupa
A57: INV00021769 | B57: Daniela Gomez Viscaino | C57: @kburkett | D57: 46202.794 | E57: 46210.341 | F57: 181.1 | G57: 7.5 | H57: 2026-06 | I57: Coupa
A58: INV00021673 | B58: Ashley Hudson | C58: @kburkett | D58: 46202.822 | E58: 46202.9 | F58: 1.9 | G58: 0.1 | H58: 2026-06 | I58: Taulia
A59: INV00022143 | B59: Daniela Gomez Viscaino | C59: @dreimers | D59: 46203.462 | E59: 46218.473 | F59: 360.3 | G59: 15 | H59: 2026-06 | I59: Ariba
A60: INV00019962 | B60: Elías Chávez Zamorano | C60: @dreimers | D60: 46203.552 | E60: 46204.506 | F60: 22.9 | G60: 1 | H60: 2026-06 | I60: Ariba
... A79: 465391 | B79: George Kahy | C79: @dreimers | D79: 46212.958 | E79: 46213.498 | F79: 13 | G79: 0.5 | H79: 2026-07 | I79: Ariba
B80: Andres Prieto | C80: @dreimers | D80: 46213.661 | E80: 46216.506 | F80: 68.3 | G80: 2.8 | H80: 2026-07 | I80: Sin dato
A81: 471288 | B81: Alejandro Salazar Copado | C81: @dreimers | D81: 46213.682 | E81: 46216.509 | F81: 67.8 | G81: 2.8 | H81: 2026-07 | I81: Ariba
A82: 471302 | B82: Alejandro Salazar Copado | C82: @dreimers | D82: 46216.4 | E82: 46218.468 | F82: 49.6 | G82: 2.1 | H82: 2026-07 | I82: Ariba
A83: 471289 | B83: Karla Tellez | C83: @dreimers | D83: 46216.464 | E83: 46216.515 | F83: 1.2 | G83: 0.1 | H83: 2026-07 | I83: Ariba
A84: INV00023439 | B84: Cindy Espinola | C84: @dreimers | D84: 46216.597 | E84: 46216.602 | F84: 0.1 | G84: 0 | H84: 2026-07 | I84: Coupa
A85: INV00020373 | B85: Daiki Hayashi | C85: @dreimers | D85: 46216.982 | E85: 46218.468 | F85: 35.7 | G85: 1.5 | H85: 2026-07 | I85: Coupa
A86: INV00022437 | B86: Mariana Senkovych | C86: @dreimers | D86: 46217.392 | E86: 46218.552 | F86: 27.8 | G86: 1.2 | H86: 2026-07 | I86: Ariba
A87: 377444 | B87: Nathan Smith | C87: @dreimers | D87: 46217.45 | E87: 46245.381 | F87: 670.4 | G87: 27.9 | H87: 2026-07 | I87: Portal por URL
A88: INV00023643 | B88: Diego Cué Vázquez | C88: @dreimers | D88: 46219.51 | E88: 46219.591 | F88: 1.9 | G88: 0.1 | H88: 2026-07 | I88: Google
A89: 468661 | B89: Erick Z. Cabrera | C89: @dreimers | D89: 46219.579 | E89: 46223.593 | F89: 96.3 | G89: 4 | H89: 2026-07 | I89: Vendor Invoice Managem
A90: INV00023799 | B90: Cindy Espinola | C90: @dreimers | D90: 46220.596 | E90: 46223.593 | F90: 71.9 | G90: 3 | H90: 2026-07 | I90: Tungsten
A91: INV00020544 | B91: Nikhil Anjikar | C91: @dreimers | D91: 46223.573 | E91: 46223.596 | F91: 0.6 | G91: 0 | H91: 2026-07 | I91: Coupa
A92: INV00023799 | B92: Mariana Senkovych | C92: @dreimers | D92: 46224.192 | E92: 46224.448 | F92: 6.1 | G92: 0.3 | H92: 2026-07 | I92: Tradeshift
... A103: 421511 | B103: Saiyon Tanaka | C103: @dreimers | D103: 46229.832 | E103: 46230.459 | F103: 15.1 | G103: 0.6 | H103: 2026-07 | I103: Coupa
B104: Andres Prieto | D104: 46230.401 | H104: 2026-07 | I104: Sap Business Network
A105: PR740566 | B105: Mariano Muniain | C105: @dreimers | D105: 46230.412 | E105: 46230.499 | F105: 2.1 | G105: 0.1 | H105: 2026-07 | I105: Ariba
A106: INV00023572 | B106: Pamella Covarrubias | C106: @dreimers | D106: 46230.44 | E106: 46230.472 | F106: 0.8 | G106: 0 | H106: 2026-07 | I106: Ariba
A107: INV00020848 | B107: Fernando Anaya | C107: @dreimers | D107: 46231.341 | E107: 46231.347 | F107: 0.1 | G107: 0 | H107: 2026-07 | I107: Ariba
A108: INV00023030 | B108: Viki Kovaliv | C108: @dreimers | D108: 46232.534 | E108: 46232.571 | F108: 0.9 | G108: 0 | H108: 2026-07 | I108: Transcepta
A109: INV00024052 | B109: Andrea Juarez | C109: @dreimers | D109: 46232.564 | E109: 46232.585 | F109: 0.5 | G109: 0 | H109: 2026-07 | I109: Ariba
A110: 465215 | B110: Sebastian Novelo | C110: @dreimers | D110: 46232.618 | E110: 46233.347 | F110: 17.5 | G110: 0.7 | H110: 2026-07 | I110: Ap National Security S
A111: INV00024404 | B111: Jose Novelo | C111: @dreimers | D111: 46232.689 | E111: 46233.338 | F111: 15.6 | G111: 0.6 | H111: 2026-07 | I111: Ariba
A112: INV00023868 | B112: Fernando Anaya | C112: @dreimers | D112: 46233.479 | E112: 46233.568 | F112: 2.1 | G112: 0.1 | H112: 2026-07 | I112: Ariba
B113: Mario Cortés | C113: @dreimers | D113: 46233.649 | E113: 46234.424 | F113: 18.6 | G113: 0.8 | H113: 2026-07 | I113: Ariba
A114: 470461 | B114: Aity Sánchez Sandoval | D114: 46233.687 | E114: 46234.426 | F114: 17.7 | G114: 0.7 | H114: 2026-07 | I114: Transcepta
A115: 465369 | B115: Aity Sánchez Sandoval | C115: @dreimers | D115: 46233.689 | E115: 46234.427 | F115: 17.7 | G115: 0.7 | H115: 2026-07 | I115: Transcepta
B116: Vamshi Dacha | C116: @dreimers | D116: 46234.347 | E116: 46234.37 | F116: 0.5 | G116: 0 | H116: 2026-07 | I116: Ariba
A117: INV00023786 | B117: Daniela Gomez Viscaino | C117: @dreimers | D117: 46234.503 | E117: 46234.512 | F117: 0.2 | G117: 0 | H117: 2026-07 | I117: Taulia
A118: INV00023795 | B118: Daniela Gomez Viscaino | C118: @dreimers | D118: 46234.507 | E118: 46234.512 | F118: 0.1 | G118: 0 | H118: 2026-07 | I118: Ariba
A119: INV00024825 | B119: Cindy Espinola | C119: @dreimers | D119: 46234.558 | E119: 46234.582 | F119: 0.6 | G119: 0 | H119: 2026-07 | I119: Ariba
A120: INV00024822 | B120: Cindy Espinola | C120: @dreimers | D120: 46234.563 | E120: 46234.582 | F120: 0.5 | G120: 0 | H120: 2026-07 | I120: Ariba
A121: INV00024823 | B121: Cindy Espinola | C121: @dreimers | D121: 46234.568 | E121: 46234.583 | F121: 0.4 | G121: 0 | H121: 2026-07 | I121: Ariba
A122: INV00024709 | B122: Andrea Juarez | C122: @dreimers | D122: 46234.578 | E122: 46234.584 | F122: 0.2 | G122: 0 | H122: 2026-07 | I122: Ariba
A123: 398434 | B123: Nathan Smith | C123: @dreimers | D123: 46237.462 | E123: 46245.386 | F123: 190.2 | G123: 7.9 | H123: 2026-08 | I123: Portal por URL
A124: 434853 | B124: Nathan Smith | C124: @dreimers | D124: 46237.464 | E124: 46245.386 | F124: 190.1 | G124: 7.9 | H124: 2026-08 | I124: Portal por URL
A125: INV00023868 | B125: Fernando Anaya | C125: @dreimers | D125: 46238.471 | E125: 46238.504 | F125: 0.8 | G125: 0 | H125: 2026-08 | I125: Ariba
A126: INV00022989 | B126: Fernando Anaya | C126: @dreimers | D126: 46238.493 | E126: 46238.505 | F126: 0.3 | G126: 0 | H126: 2026-08 | I126: Coupa
A127: INV00025400 | B127: Diego Cué Vázquez | C127: @dreimers | D127: 46238.558 | E127: 46238.582 | F127: 0.6 | G127: 0 | H127: 2026-08 | I127: Ariba
A128: 468617 | B128: Maria Granja | C128: @dreimers | D128: 46238.627 | E128: 46245.387 | F128: 162.2 | G128: 6.8 | H128: 2026-08 | I128: Ariba
B129: Mario Cortés | C129: @dreimers | D129: 46238.934 | E129: 46239.459 | F129: 12.6 | G129: 0.5 | H129: 2026-08 | I129: Ariba
A130: INV00024404 | B130: Abril Marmolejo Portillo | C130: @dreimers | D130: 46239.466 | E130: 46239.472 | F130: 0.2 | G130: 0 | H130: 2026-08 | I130: Ariba
A131: INV00022895 | B131: Fernando Anaya | C131: @dreimers | D131: 46240.387 | E131: 46240.39 | F131: 0 | G131: 0 | H131: 2026-08 | I131: Coupa
A132: 471590 | B132: Paulina Paredes Fernández Turueño | C132: @dreimers | D132: 46241.591 | E132: 46245.387 | F132: 91.1 | G132: 3.8 | H132: 2026-08 | I132: Oracle
A133: INV00021780 | B133: Fernando Anaya | C133: @dreimers | D133: 46245.448 | E133: 46245.482 | F133: 0.8 | G133: 0 | H133: 2026-08 | I133: Coupa
A134: Best Buy MR Invoice | B134: Dan Deming | C134: @dreimers | D134: 46245.465 | E134: 46246.604 | F134: 27.3 | G134: 1.1 | H134: 2026-08 | I134: Ariba
A135: INV00025297 | B135: Andrea Juarez | C135: @dreimers | D135: 46246.554 | E135: 46246.607 | F135: 1.3 | G135: 0.1 | H135: 2026-08 | I135: Coupa
A136: INV00025767 | B136: Andrea Juarez | C136: @dreimers | D136: 46246.555 | E136: 46246.611 | F136: 1.3 | G136: 0.1 | H136: 2026-08 | I136: Ariba
A137: INV00025534 | B137: Mario Cortés | C137: @aprilj | D137: 46247.405 | E137: 46247.413 | F137: 0.2 | G137: 0 | H137: 2026-08 | I137: Coupa
A138: INV00026113 | B138: Cindy Espinola | C138: @aprilj | D138: 46247.455 | E138: 46247.555 | F138: 2.4 | G138: 0.1 | H138: 2026-08 | I138: Ariba
A139: 466580 | B139: Mario Cortés | C139: @dreimers | D139: 46247.584 | E139: 46266.738 | F139: 459.7 | G139: 19.2 | H139: 2026-08 | I139: Www.Vendors.Gov.Sg
B140: Mario Cortés | D140: 46251.606 | H140: 2026-08 | I140: Taulia
B141: Andres Prieto | C141: @dreimers | D141: 46251.654 | E141: 46252.315 | F141: 15.9 | G141: 0.7 | H141: 2026-08 | I141: Taulia
A142: INV00025761 | B142: Andrea Juarez | C142: @dreimers | D142: 46251.785 | E142: 46252.385 | F142: 14.4 | G142: 0.6 | H142: 2026-08 | I142: Coupa
A143: INV00025652 | B143: George Kahy | C143: @aprilj | D143: 46251.9 | E143: 46252.299 | F143: 9.6 | G143: 0.4 | H143: 2026-08 | I143: Coupa
A144: INV00023883 | B144: George Kahy | C144: @aprilj | D144: 46252.107 | E144: 46252.301 | F144: 4.7 | G144: 0.2 | H144: 2026-08 | I144: Ariba
A145: INV00025761 | B145: Alejandro Salazar Copado | C145: @dreimers | D145: 46252.486 | E145: 46252.489 | F145: 0.1 | G145: 0 | H145: 2026-08 | I145: Coupa
A146: INV00026379 | B146: Diego Cué Vázquez | C146: @dreimers | D146: 46252.527 | E146: 46252.578 | F146: 1.2 | G146: 0.1 | H146: 2026-08 | I146: Coupa
A147: INV00026390 | B147: Yulian Trishch | C147: @dreimers | D147: 46253.148 | E147: 46253.497 | F147: 8.4 | G147: 0.3 | H147: 2026-08 | I147: Tradeinterop
A148: 467656 | B148: Viki Kovaliv | C148: @dreimers | D148: 46253.226 | E148: 46254.627 | F148: 33.6 | G148: 1.4 | H148: 2026-08 | I148: Oracle
A149: INV00025781 | B149: Sebastian Novelo | C149: @dreimers | D149: 46254.657 | E149: 46254.675 | F149: 0.4 | G149: 0 | H149: 2026-08 | I149: Ariba
A150: 471857 | B150: Jose Novelo | C150: @dreimers | D150: 46255.44 | H150: 2026-08 | I150: Peppol
A151: INV00023536 | B151: Yulian Trishch | C151: @dreimers | D151: 46258.34 | E151: 46258.681 | F151: 8.2 | G151: 0.3 | H151: 2026-08 | I151: Coupa
A152: INV00026412 | B152: Alejandro Salazar Copado | C152: @dreimers | D152: 46258.53 | E152: 46258.693 | F152: 3.9 | G152: 0.2 | H152: 2026-08 | I152: Coupa
...

Sheet Atipicos Agosto (>7 dias)
A1: CASOS ATÍPICOS DE AGOSTO — Resolución mayor a 7 días
A2: 3 uploads de agosto superaron los 7 días.
A4: Invoice Number | B4: Submitted By | C4: Collector assigned | D4: Portal | E4: Submit Timestamp | F4: Resolved Timestamp | G4: Días de resolución
A5: 466580 | B5: Mario Cortés | C5: @dreimers | D5: Www.Vendors.Gov.Sg | E5: 46247.584 | F5: 46266.738 | G5: =(F5-E5)
A6: 398434 | B6: Nathan Smith | C6: @dreimers | D6: Portal por URL | E6: 46237.462 | F6: 46245.386 | G6: =(F6-E6)
A7: 434853 | B7: Nathan Smith | C7: @dreimers | D7: Portal por URL | E7: 46237.464 | F7: 46245.386 | G7: =(F7-E7)
F9: Promedio atípicos: | G9: =ROUND(AVERAGE(G5:G7),1)
